TestRepeater.py
robotframework_testrepeater-1.2.2.dist-info/licenses/LICENSE
robotframework_testrepeater-1.2.2.dist-info/METADATA
robotframework_testrepeater-1.2.2.dist-info/WHEEL
robotframework_testrepeater-1.2.2.dist-info/top_level.txt
robotframework_testrepeater-1.2.2.dist-info/RECORD
