Metadata-Version: 2.4
Name: robotframework-testrepeater
Version: 1.2.2
Summary: A listener to repeat testscases for given iterations.
Author: abi-sheak, reharish
Author-email: abisheakkumarasamy@gmail.com, rengarajharish@gmail.com
License: Apache License 2.0
License-File: LICENSE
Requires-Dist: robotframework
Dynamic: author
Dynamic: author-email
Dynamic: description
Dynamic: description-content-type
Dynamic: license
Dynamic: license-file
Dynamic: requires-dist
Dynamic: summary
